{
  "Ads": [
    {
      "select_main_ads": "ADMOB",
      "select_backup_ads":"APPLOVIN-D",
      "main_ads_banner": "ca-app-pub-3940256099942544/630097811x",
      "main_ads_intertitial":"ca-app-pub-3940256099942544/103317371x",
      "native_for_admob":"ca-app-pub-3940256099942544/224769611x",
      "backup_ads_banner":"qwert12345",
      "backup_ads_intertitial":"qwert12345",
      "interval_intertitial": 5,
      "initialize_sdk":"null",
      "initialize_sdk_backup_ads":"null",
      "high_paying_keyword_1": "",
      "high_paying_keyword_2": "",
      "high_paying_keyword_3": "",
      "high_paying_keyword_4": "",
      "high_paying_keyword_5": "",
      "status_app": "0",
      "link_redirect": "https://"
    }
  ],
  "More":
  [
    
  ],

  "Categories": [
    {
      "id": 1,
      "name_category": "BTS V Wallpaper 1",
      "image": "file:///android_asset/image/itxem1.webp"

    },
    {
      "id": 2,
      "name_category": "BTS V Wallpaper 2",
      "image": "file:///android_asset/image/itxem51.webp"

    },
    {
      "id": 3,
      "name_category": "BTS V Wallpaper 3",
      "image": "file:///android_asset/image/itxem101.webp"

    },
    {
      "id": 4,
      "name_category": "BTS V Wallpaper 4",
      "image": "file:///android_asset/image/itxem151.webp"

    },
    {
      "id": 5,
      "name_category": "BTS V Wallpaper 5",
      "image": "file:///android_asset/image/itxem201.webp"

    },
    {
      "id": 6,
      "name_category": "BTS V Wallpaper 6",
      "image": "file:///android_asset/image/itxem251.webp"

    }
  ],

  "Data":
  [
    {
      "id":1,
      "name_category": "BTS V Wallpaper 1",
      "title":"BTS V Wallpaper",
      "image":"file:///android_asset/image/itxem1.webp"
    },
    {
      "id": 2,
      "name_category": "BTS V Wallpaper 1",
      "title": "BTS V Wallpaper",
      "image": "file:///android_asset/image/itxem2.webp"
    },
    {
      "id":3,
      "name_category": "BTS V Wallpaper 1",
      "title":"BTS V Wallpaper",
      "image":"file:///android_asset/image/itxem3.webp"
    },
    {
      "id":4,
      "name_category": "BTS V Wallpaper 1",
      "title":"BTS V Wallpaper",
      "image":"file:///android_asset/image/itxem4.webp"
    },
    {
      "id":5,
      "name_category": "BTS V Wallpaper 1",
      "title":"BTS V Wallpaper",
      "image":"file:///android_asset/image/itxem5.webp"
    },
    {
      "id":6,
      "name_category": "BTS V Wallpaper 1",
      "title":"BTS V Wallpaper",
      "image":"file:///android_asset/image/itxem6.webp"
    },
    {
      "id":7,
      "name_category": "BTS V Wallpaper 1",
      "title":"BTS V Wallpaper",
      "image":"file:///android_asset/image/itxem7.webp"
    },
    {
      "id":8,
      "name_category": "BTS V Wallpaper 1",
      "title":"BTS V Wallpaper",
      "image":"file:///android_asset/image/itxem8.webp"
    },
    {
      "id":9,
      "name_category": "BTS V Wallpaper 1",
      "title":"BTS V Wallpaper",
      "image":"file:///android_asset/image/itxem9.webp"
    },
    {
      "id":10,
      "name_category": "BTS V Wallpaper 1",
      "title":"BTS V Wallpaper",
      "image":"file:///android_asset/image/itxem10.webp"
    },
	{
      "id":11,
      "name_category": "BTS V Wallpaper 1",
      "title":"BTS V Wallpaper",
      "image":"file:///android_asset/image/itxem11.webp"
    },
    {
      "id": 12,
      "name_category": "BTS V Wallpaper 1",
      "title": "BTS V Wallpaper",
      "image": "file:///android_asset/image/itxem12.webp"
    },
    {
      "id":13,
      "name_category": "BTS V Wallpaper 1",
      "title":"BTS V Wallpaper",
      "image":"file:///android_asset/image/itxem13.webp"
    },
    {
      "id":14,
      "name_category": "BTS V Wallpaper 1",
      "title":"BTS V Wallpaper",
      "image":"file:///android_asset/image/itxem14.webp"
    },
    {
      "id":15,
      "name_category": "BTS V Wallpaper 1",
      "title":"BTS V Wallpaper",
      "image":"file:///android_asset/image/itxem15.webp"
    },
    {
      "id":16,
      "name_category": "BTS V Wallpaper 1",
      "title":"BTS V Wallpaper",
      "image":"file:///android_asset/image/itxem16.webp"
    },
    {
      "id":17,
      "name_category": "BTS V Wallpaper 1",
      "title":"BTS V Wallpaper",
      "image":"file:///android_asset/image/itxem17.webp"
    },
    {
      "id":18,
      "name_category": "BTS V Wallpaper 1",
      "title":"BTS V Wallpaper",
      "image":"file:///android_asset/image/itxem18.webp"
    },
    {
      "id":19,
      "name_category": "BTS V Wallpaper 1",
      "title":"BTS V Wallpaper",
      "image":"file:///android_asset/image/itxem19.webp"
    },
    {
      "id":20,
      "name_category": "BTS V Wallpaper 1",
      "title":"BTS V Wallpaper",
      "image":"file:///android_asset/image/itxem20.webp"
    },
	{
      "id":21,
      "name_category": "BTS V Wallpaper 1",
      "title":"BTS V Wallpaper",
      "image":"file:///android_asset/image/itxem21.webp"
    },
    {
      "id": 22,
      "name_category": "BTS V Wallpaper 1",
      "title": "BTS V Wallpaper",
      "image": "file:///android_asset/image/itxem22.webp"
    },
    {
      "id":23,
      "name_category": "BTS V Wallpaper 1",
      "title":"BTS V Wallpaper",
      "image":"file:///android_asset/image/itxem23.webp"
    },
    {
      "id":24,
      "name_category": "BTS V Wallpaper 1",
      "title":"BTS V Wallpaper",
      "image":"file:///android_asset/image/itxem24.webp"
    },
    {
      "id":25,
      "name_category": "BTS V Wallpaper 1",
      "title":"BTS V Wallpaper",
      "image":"file:///android_asset/image/itxem25.webp"
    },
    {
      "id":26,
      "name_category": "BTS V Wallpaper 1",
      "title":"BTS V Wallpaper",
      "image":"file:///android_asset/image/itxem26.webp"
    },
    {
      "id":27,
      "name_category": "BTS V Wallpaper 1",
      "title":"BTS V Wallpaper",
      "image":"file:///android_asset/image/itxem27.webp"
    },
    {
      "id":28,
      "name_category": "BTS V Wallpaper 1",
      "title":"BTS V Wallpaper",
      "image":"file:///android_asset/image/itxem28.webp"
    },
    {
      "id":29,
      "name_category": "BTS V Wallpaper 1",
      "title":"BTS V Wallpaper",
      "image":"file:///android_asset/image/itxem29.webp"
    },
    {
      "id":30,
      "name_category": "BTS V Wallpaper 1",
      "title":"BTS V Wallpaper",
      "image":"file:///android_asset/image/itxem30.webp"
    },
	{
      "id":31,
      "name_category": "BTS V Wallpaper 1",
      "title":"BTS V Wallpaper",
      "image":"file:///android_asset/image/itxem31.webp"
    },
    {
      "id": 32,
      "name_category": "BTS V Wallpaper 1",
      "title": "BTS V Wallpaper",
      "image": "file:///android_asset/image/itxem32.webp"
    },
    {
      "id":33,
      "name_category": "BTS V Wallpaper 1",
      "title":"BTS V Wallpaper",
      "image":"file:///android_asset/image/itxem33.webp"
    },
    {
      "id":34,
      "name_category": "BTS V Wallpaper 1",
      "title":"BTS V Wallpaper",
      "image":"file:///android_asset/image/itxem34.webp"
    },
    {
      "id":35,
      "name_category": "BTS V Wallpaper 1",
      "title":"BTS V Wallpaper",
      "image":"file:///android_asset/image/itxem35.webp"
    },
    {
      "id":36,
      "name_category": "BTS V Wallpaper 1",
      "title":"BTS V Wallpaper",
      "image":"file:///android_asset/image/itxem36.webp"
    },
    {
      "id":37,
      "name_category": "BTS V Wallpaper 1",
      "title":"BTS V Wallpaper",
      "image":"file:///android_asset/image/itxem37.webp"
    },
    {
      "id":38,
      "name_category": "BTS V Wallpaper 1",
      "title":"BTS V Wallpaper",
      "image":"file:///android_asset/image/itxem38.webp"
    },
    {
      "id":39,
      "name_category": "BTS V Wallpaper 1",
      "title":"BTS V Wallpaper",
      "image":"file:///android_asset/image/itxem39.webp"
    },
    {
      "id":40,
      "name_category": "BTS V Wallpaper 1",
      "title":"BTS V Wallpaper",
      "image":"file:///android_asset/image/itxem40.webp"
    },
	{
      "id":41,
      "name_category": "BTS V Wallpaper 1",
      "title":"BTS V Wallpaper",
      "image":"file:///android_asset/image/itxem41.webp"
    },
    {
      "id": 42,
      "name_category": "BTS V Wallpaper 1",
      "title": "BTS V Wallpaper",
      "image": "file:///android_asset/image/itxem42.webp"
    },
    {
      "id":43,
      "name_category": "BTS V Wallpaper 1",
      "title":"BTS V Wallpaper",
      "image":"file:///android_asset/image/itxem43.webp"
    },
    {
      "id":44,
      "name_category": "BTS V Wallpaper 1",
      "title":"BTS V Wallpaper",
      "image":"file:///android_asset/image/itxem44.webp"
    },
    {
      "id":45,
      "name_category": "BTS V Wallpaper 1",
      "title":"BTS V Wallpaper",
      "image":"file:///android_asset/image/itxem45.webp"
    },
    {
      "id":46,
      "name_category": "BTS V Wallpaper 1",
      "title":"BTS V Wallpaper",
      "image":"file:///android_asset/image/itxem46.webp"
    },
    {
      "id":47,
      "name_category": "BTS V Wallpaper 1",
      "title":"BTS V Wallpaper",
      "image":"file:///android_asset/image/itxem47.webp"
    },
    {
      "id":48,
      "name_category": "BTS V Wallpaper 1",
      "title":"BTS V Wallpaper",
      "image":"file:///android_asset/image/itxem48.webp"
    },
    {
      "id":49,
      "name_category": "BTS V Wallpaper 1",
      "title":"BTS V Wallpaper",
      "image":"file:///android_asset/image/itxem49.webp"
    },
    {
      "id":50,
      "name_category": "BTS V Wallpaper 1",
      "title":"BTS V Wallpaper",
      "image":"file:///android_asset/image/itxem50.webp"
    },
	{
      "id":51,
      "name_category": "BTS V Wallpaper 2",
      "title":"BTS V Wallpaper",
      "image":"file:///android_asset/image/itxem51.webp"
    },
    {
      "id": 52,
      "name_category": "BTS V Wallpaper 2",
      "title": "BTS V Wallpaper",
      "image": "file:///android_asset/image/itxem52.webp"
    },
    {
      "id":53,
      "name_category": "BTS V Wallpaper 2",
      "title":"BTS V Wallpaper",
      "image":"file:///android_asset/image/itxem53.webp"
    },
    {
      "id":54,
      "name_category": "BTS V Wallpaper 2",
      "title":"BTS V Wallpaper",
      "image":"file:///android_asset/image/itxem54.webp"
    },
    {
      "id":55,
      "name_category": "BTS V Wallpaper 2",
      "title":"BTS V Wallpaper",
      "image":"file:///android_asset/image/itxem55.webp"
    },
    {
      "id":56,
      "name_category": "BTS V Wallpaper 2",
      "title":"BTS V Wallpaper",
      "image":"file:///android_asset/image/itxem56.webp"
    },
    {
      "id":57,
      "name_category": "BTS V Wallpaper 2",
      "title":"BTS V Wallpaper",
      "image":"file:///android_asset/image/itxem57.webp"
    },
    {
      "id":58,
      "name_category": "BTS V Wallpaper 2",
      "title":"BTS V Wallpaper",
      "image":"file:///android_asset/image/itxem58.webp"
    },
    {
      "id":59,
      "name_category": "BTS V Wallpaper 2",
      "title":"BTS V Wallpaper",
      "image":"file:///android_asset/image/itxem59.webp"
    },
    {
      "id":60,
      "name_category": "BTS V Wallpaper 2",
      "title":"BTS V Wallpaper",
      "image":"file:///android_asset/image/itxem60.webp"
    },
	{
      "id":61,
      "name_category": "BTS V Wallpaper 2",
      "title":"BTS V Wallpaper",
      "image":"file:///android_asset/image/itxem61.webp"
    },
    {
      "id": 62,
      "name_category": "BTS V Wallpaper 2",
      "title": "BTS V Wallpaper",
      "image": "file:///android_asset/image/itxem62.webp"
    },
    {
      "id":63,
      "name_category": "BTS V Wallpaper 2",
      "title":"BTS V Wallpaper",
      "image":"file:///android_asset/image/itxem63.webp"
    },
    {
      "id":64,
      "name_category": "BTS V Wallpaper 2",
      "title":"BTS V Wallpaper",
      "image":"file:///android_asset/image/itxem64.webp"
    },
    {
      "id":65,
      "name_category": "BTS V Wallpaper 2",
      "title":"BTS V Wallpaper",
      "image":"file:///android_asset/image/itxem65.webp"
    },
    {
      "id":66,
      "name_category": "BTS V Wallpaper 2",
      "title":"BTS V Wallpaper",
      "image":"file:///android_asset/image/itxem66.webp"
    },
    {
      "id":67,
      "name_category": "BTS V Wallpaper 2",
      "title":"BTS V Wallpaper",
      "image":"file:///android_asset/image/itxem67.webp"
    },
    {
      "id":68,
      "name_category": "BTS V Wallpaper 2",
      "title":"BTS V Wallpaper",
      "image":"file:///android_asset/image/itxem68.webp"
    },
    {
      "id":69,
      "name_category": "BTS V Wallpaper 2",
      "title":"BTS V Wallpaper",
      "image":"file:///android_asset/image/itxem69.webp"
    },
    {
      "id":70,
      "name_category": "BTS V Wallpaper 2",
      "title":"BTS V Wallpaper",
      "image":"file:///android_asset/image/itxem70.webp"
    },
	{
      "id":71,
      "name_category": "BTS V Wallpaper 2",
      "title":"BTS V Wallpaper",
      "image":"file:///android_asset/image/itxem71.webp"
    },
    {
      "id": 72,
      "name_category": "BTS V Wallpaper 2",
      "title": "BTS V Wallpaper",
      "image": "file:///android_asset/image/itxem72.webp"
    },
    {
      "id":73,
      "name_category": "BTS V Wallpaper 2",
      "title":"BTS V Wallpaper",
      "image":"file:///android_asset/image/itxem73.webp"
    },
    {
      "id":74,
      "name_category": "BTS V Wallpaper 2",
      "title":"BTS V Wallpaper",
      "image":"file:///android_asset/image/itxem74.webp"
    },
    {
      "id":75,
      "name_category": "BTS V Wallpaper 2",
      "title":"BTS V Wallpaper",
      "image":"file:///android_asset/image/itxem75.webp"
    },
    {
      "id":76,
      "name_category": "BTS V Wallpaper 2",
      "title":"BTS V Wallpaper",
      "image":"file:///android_asset/image/itxem76.webp"
    },
    {
      "id":77,
      "name_category": "BTS V Wallpaper 2",
      "title":"BTS V Wallpaper",
      "image":"file:///android_asset/image/itxem77.webp"
    },
    {
      "id":78,
      "name_category": "BTS V Wallpaper 2",
      "title":"BTS V Wallpaper",
      "image":"file:///android_asset/image/itxem78.webp"
    },
    {
      "id":79,
      "name_category": "BTS V Wallpaper 2",
      "title":"BTS V Wallpaper",
      "image":"file:///android_asset/image/itxem79.webp"
    },
    {
      "id":80,
      "name_category": "BTS V Wallpaper 2",
      "title":"BTS V Wallpaper",
      "image":"file:///android_asset/image/itxem80.webp"
    },
	{
      "id":81,
      "name_category": "BTS V Wallpaper 2",
      "title":"BTS V Wallpaper",
      "image":"file:///android_asset/image/itxem81.webp"
    },
    {
      "id": 82,
      "name_category": "BTS V Wallpaper 2",
      "title": "BTS V Wallpaper",
      "image": "file:///android_asset/image/itxem82.webp"
    },
    {
      "id":83,
      "name_category": "BTS V Wallpaper 2",
      "title":"BTS V Wallpaper",
      "image":"file:///android_asset/image/itxem83.webp"
    },
    {
      "id":84,
      "name_category": "BTS V Wallpaper 2",
      "title":"BTS V Wallpaper",
      "image":"file:///android_asset/image/itxem84.webp"
    },
    {
      "id":85,
      "name_category": "BTS V Wallpaper 2",
      "title":"BTS V Wallpaper",
      "image":"file:///android_asset/image/itxem85.webp"
    },
    {
      "id":86,
      "name_category": "BTS V Wallpaper 2",
      "title":"BTS V Wallpaper",
      "image":"file:///android_asset/image/itxem86.webp"
    },
    {
      "id":87,
      "name_category": "BTS V Wallpaper 2",
      "title":"BTS V Wallpaper",
      "image":"file:///android_asset/image/itxem87.webp"
    },
    {
      "id":88,
      "name_category": "BTS V Wallpaper 2",
      "title":"BTS V Wallpaper",
      "image":"file:///android_asset/image/itxem88.webp"
    },
    {
      "id":89,
      "name_category": "BTS V Wallpaper 2",
      "title":"BTS V Wallpaper",
      "image":"file:///android_asset/image/itxem89.webp"
    },
    {
      "id":90,
      "name_category": "BTS V Wallpaper 2",
      "title":"BTS V Wallpaper",
      "image":"file:///android_asset/image/itxem90.webp"
    },
	{
      "id":91,
      "name_category": "BTS V Wallpaper 2",
      "title":"BTS V Wallpaper",
      "image":"file:///android_asset/image/itxem91.webp"
    },
    {
      "id": 92,
      "name_category": "BTS V Wallpaper 2",
      "title": "BTS V Wallpaper",
      "image": "file:///android_asset/image/itxem92.webp"
    },
    {
      "id":93,
      "name_category": "BTS V Wallpaper 2",
      "title":"BTS V Wallpaper",
      "image":"file:///android_asset/image/itxem93.webp"
    },
    {
      "id":94,
      "name_category": "BTS V Wallpaper 2",
      "title":"BTS V Wallpaper",
      "image":"file:///android_asset/image/itxem94.webp"
    },
    {
      "id":95,
      "name_category": "BTS V Wallpaper 2",
      "title":"BTS V Wallpaper",
      "image":"file:///android_asset/image/itxem95.webp"
    },
    {
      "id":96,
      "name_category": "BTS V Wallpaper 2",
      "title":"BTS V Wallpaper",
      "image":"file:///android_asset/image/itxem96.webp"
    },
    {
      "id":97,
      "name_category": "BTS V Wallpaper 2",
      "title":"BTS V Wallpaper",
      "image":"file:///android_asset/image/itxem97.webp"
    },
    {
      "id":98,
      "name_category": "BTS V Wallpaper 2",
      "title":"BTS V Wallpaper",
      "image":"file:///android_asset/image/itxem98.webp"
    },
    {
      "id":99,
      "name_category": "BTS V Wallpaper 2",
      "title":"BTS V Wallpaper",
      "image":"file:///android_asset/image/itxem99.webp"
    },
    {
      "id":100,
      "name_category": "BTS V Wallpaper 2",
      "title":"BTS V Wallpaper",
      "image":"file:///android_asset/image/itxem100.webp"
    },
	{
      "id":101,
      "name_category": "BTS V Wallpaper 3",
      "title":"BTS V Wallpaper",
      "image":"file:///android_asset/image/itxem101.webp"
    },
    {
      "id":102,
      "name_category": "BTS V Wallpaper 3",
      "title": "BTS V Wallpaper",
      "image": "file:///android_asset/image/itxem102.webp"
    },
    {
      "id":103,
      "name_category": "BTS V Wallpaper 3",
      "title":"BTS V Wallpaper",
      "image":"file:///android_asset/image/itxem103.webp"
    },
    {
      "id":104,
      "name_category": "BTS V Wallpaper 3",
      "title":"BTS V Wallpaper",
      "image":"file:///android_asset/image/itxem104.webp"
    },
    {
      "id":105,
      "name_category": "BTS V Wallpaper 3",
      "title":"BTS V Wallpaper",
      "image":"file:///android_asset/image/itxem105.webp"
    },
    {
      "id":106,
      "name_category": "BTS V Wallpaper 3",
      "title":"BTS V Wallpaper",
      "image":"file:///android_asset/image/itxem106.webp"
    },
    {
      "id":107,
      "name_category": "BTS V Wallpaper 3",
      "title":"BTS V Wallpaper",
      "image":"file:///android_asset/image/itxem107.webp"
    },
    {
      "id":108,
      "name_category": "BTS V Wallpaper 3",
      "title":"BTS V Wallpaper",
      "image":"file:///android_asset/image/itxem108.webp"
    },
    {
      "id":109,
      "name_category": "BTS V Wallpaper 3",
      "title":"BTS V Wallpaper",
      "image":"file:///android_asset/image/itxem109.webp"
    },
    {
      "id":110,
      "name_category": "BTS V Wallpaper 3",
      "title":"BTS V Wallpaper",
      "image":"file:///android_asset/image/itxem110.webp"
    },
	{
      "id":111,
      "name_category": "BTS V Wallpaper 3",
      "title":"BTS V Wallpaper",
      "image":"file:///android_asset/image/itxem111.webp"
    },
    {
      "id": 112,
      "name_category": "BTS V Wallpaper 3",
      "title": "BTS V Wallpaper",
      "image": "file:///android_asset/image/itxem112.webp"
    },
    {
      "id":113,
      "name_category": "BTS V Wallpaper 3",
      "title":"BTS V Wallpaper",
      "image":"file:///android_asset/image/itxem113.webp"
    },
    {
      "id":114,
      "name_category": "BTS V Wallpaper 3",
      "title":"BTS V Wallpaper",
      "image":"file:///android_asset/image/itxem114.webp"
    },
    {
      "id":115,
      "name_category": "BTS V Wallpaper 3",
      "title":"BTS V Wallpaper",
      "image":"file:///android_asset/image/itxem115.webp"
    },
    {
      "id":116,
      "name_category": "BTS V Wallpaper 3",
      "title":"BTS V Wallpaper",
      "image":"file:///android_asset/image/itxem116.webp"
    },
    {
      "id":117,
      "name_category": "BTS V Wallpaper 3",
      "title":"BTS V Wallpaper",
      "image":"file:///android_asset/image/itxem117.webp"
    },
    {
      "id":118,
      "name_category": "BTS V Wallpaper 3",
      "title":"BTS V Wallpaper",
      "image":"file:///android_asset/image/itxem118.webp"
    },
    {
      "id":119,
      "name_category": "BTS V Wallpaper 3",
      "title":"BTS V Wallpaper",
      "image":"file:///android_asset/image/itxem119.webp"
    },
    {
      "id":120,
      "name_category": "BTS V Wallpaper 3",
      "title":"BTS V Wallpaper",
      "image":"file:///android_asset/image/itxem120.webp"
    },
	{
      "id":121,
      "name_category": "BTS V Wallpaper 3",
      "title":"BTS V Wallpaper",
      "image":"file:///android_asset/image/itxem121.webp"
    },
    {
      "id": 122,
      "name_category": "BTS V Wallpaper 3",
      "title": "BTS V Wallpaper",
      "image": "file:///android_asset/image/itxem122.webp"
    },
    {
      "id":123,
      "name_category": "BTS V Wallpaper 3",
      "title":"BTS V Wallpaper",
      "image":"file:///android_asset/image/itxem123.webp"
    },
    {
      "id":124,
      "name_category": "BTS V Wallpaper 3",
      "title":"BTS V Wallpaper",
      "image":"file:///android_asset/image/itxem124.webp"
    },
    {
      "id":125,
      "name_category": "BTS V Wallpaper 3",
      "title":"BTS V Wallpaper",
      "image":"file:///android_asset/image/itxem125.webp"
    },
    {
      "id":126,
      "name_category": "BTS V Wallpaper 3",
      "title":"BTS V Wallpaper",
      "image":"file:///android_asset/image/itxem126.webp"
    },
    {
      "id":127,
      "name_category": "BTS V Wallpaper 3",
      "title":"BTS V Wallpaper",
      "image":"file:///android_asset/image/itxem127.webp"
    },
    {
      "id":128,
      "name_category": "BTS V Wallpaper 3",
      "title":"BTS V Wallpaper",
      "image":"file:///android_asset/image/itxem128.webp"
    },
    {
      "id":129,
      "name_category": "BTS V Wallpaper 3",
      "title":"BTS V Wallpaper",
      "image":"file:///android_asset/image/itxem129.webp"
    },
    {
      "id":130,
      "name_category": "BTS V Wallpaper 3",
      "title":"BTS V Wallpaper",
      "image":"file:///android_asset/image/itxem130.webp"
    },
	{
      "id":131,
      "name_category": "BTS V Wallpaper 3",
      "title":"BTS V Wallpaper",
      "image":"file:///android_asset/image/itxem131.webp"
    },
    {
      "id": 132,
      "name_category": "BTS V Wallpaper 3",
      "title": "BTS V Wallpaper",
      "image": "file:///android_asset/image/itxem132.webp"
    },
    {
      "id":133,
      "name_category": "BTS V Wallpaper 3",
      "title":"BTS V Wallpaper",
      "image":"file:///android_asset/image/itxem133.webp"
    },
    {
      "id":134,
      "name_category": "BTS V Wallpaper 3",
      "title":"BTS V Wallpaper",
      "image":"file:///android_asset/image/itxem134.webp"
    },
    {
      "id":135,
      "name_category": "BTS V Wallpaper 3",
      "title":"BTS V Wallpaper",
      "image":"file:///android_asset/image/itxem135.webp"
    },
    {
      "id":136,
      "name_category": "BTS V Wallpaper 3",
      "title":"BTS V Wallpaper",
      "image":"file:///android_asset/image/itxem136.webp"
    },
    {
      "id":137,
      "name_category": "BTS V Wallpaper 3",
      "title":"BTS V Wallpaper",
      "image":"file:///android_asset/image/itxem137.webp"
    },
    {
      "id":138,
      "name_category": "BTS V Wallpaper 3",
      "title":"BTS V Wallpaper",
      "image":"file:///android_asset/image/itxem138.webp"
    },
    {
      "id":139,
      "name_category": "BTS V Wallpaper 3",
      "title":"BTS V Wallpaper",
      "image":"file:///android_asset/image/itxem139.webp"
    },
    {
      "id":140,
      "name_category": "BTS V Wallpaper 3",
      "title":"BTS V Wallpaper",
      "image":"file:///android_asset/image/itxem140.webp"
    },
	{
      "id":141,
      "name_category": "BTS V Wallpaper 3",
      "title":"BTS V Wallpaper",
      "image":"file:///android_asset/image/itxem141.webp"
    },
    {
      "id": 142,
      "name_category": "BTS V Wallpaper 3",
      "title": "BTS V Wallpaper",
      "image": "file:///android_asset/image/itxem142.webp"
    },
    {
      "id":143,
      "name_category": "BTS V Wallpaper 3",
      "title":"BTS V Wallpaper",
      "image":"file:///android_asset/image/itxem143.webp"
    },
    {
      "id":144,
      "name_category": "BTS V Wallpaper 3",
      "title":"BTS V Wallpaper",
      "image":"file:///android_asset/image/itxem144.webp"
    },
    {
      "id":145,
      "name_category": "BTS V Wallpaper 3",
      "title":"BTS V Wallpaper",
      "image":"file:///android_asset/image/itxem145.webp"
    },
    {
      "id":146,
      "name_category": "BTS V Wallpaper 3",
      "title":"BTS V Wallpaper",
      "image":"file:///android_asset/image/itxem146.webp"
    },
    {
      "id":147,
      "name_category": "BTS V Wallpaper 3",
      "title":"BTS V Wallpaper",
      "image":"file:///android_asset/image/itxem147.webp"
    },
    {
      "id":148,
      "name_category": "BTS V Wallpaper 3",
      "title":"BTS V Wallpaper",
      "image":"file:///android_asset/image/itxem148.webp"
    },
    {
      "id":149,
      "name_category": "BTS V Wallpaper 3",
      "title":"BTS V Wallpaper",
      "image":"file:///android_asset/image/itxem149.webp"
    },
    {
      "id":150,
      "name_category": "BTS V Wallpaper 3",
      "title":"BTS V Wallpaper",
      "image":"file:///android_asset/image/itxem150.webp"
    },
	{
      "id":151,
      "name_category": "BTS V Wallpaper 4",
      "title":"BTS V Wallpaper",
      "image":"file:///android_asset/image/itxem151.webp"
    },
    {
      "id": 152,
      "name_category": "BTS V Wallpaper 4",
      "title": "BTS V Wallpaper",
      "image": "file:///android_asset/image/itxem152.webp"
    },
    {
      "id":153,
      "name_category": "BTS V Wallpaper 4",
      "title":"BTS V Wallpaper",
      "image":"file:///android_asset/image/itxem153.webp"
    },
    {
      "id":154,
      "name_category": "BTS V Wallpaper 4",
      "title":"BTS V Wallpaper",
      "image":"file:///android_asset/image/itxem154.webp"
    },
    {
      "id":155,
      "name_category": "BTS V Wallpaper 4",
      "title":"BTS V Wallpaper",
      "image":"file:///android_asset/image/itxem155.webp"
    },
    {
      "id":156,
      "name_category": "BTS V Wallpaper 4",
      "title":"BTS V Wallpaper",
      "image":"file:///android_asset/image/itxem156.webp"
    },
    {
      "id":157,
      "name_category": "BTS V Wallpaper 4",
      "title":"BTS V Wallpaper",
      "image":"file:///android_asset/image/itxem157.webp"
    },
    {
      "id":158,
      "name_category": "BTS V Wallpaper 4",
      "title":"BTS V Wallpaper",
      "image":"file:///android_asset/image/itxem158.webp"
    },
    {
      "id":159,
      "name_category": "BTS V Wallpaper 4",
      "title":"BTS V Wallpaper",
      "image":"file:///android_asset/image/itxem159.webp"
    },
    {
      "id":160,
      "name_category": "BTS V Wallpaper 4",
      "title":"BTS V Wallpaper",
      "image":"file:///android_asset/image/itxem160.webp"
    },
	{
      "id":161,
      "name_category": "BTS V Wallpaper 4",
      "title":"BTS V Wallpaper",
      "image":"file:///android_asset/image/itxem161.webp"
    },
    {
      "id": 162,
      "name_category": "BTS V Wallpaper 4",
      "title": "BTS V Wallpaper",
      "image": "file:///android_asset/image/itxem162.webp"
    },
    {
      "id":163,
      "name_category": "BTS V Wallpaper 4",
      "title":"BTS V Wallpaper",
      "image":"file:///android_asset/image/itxem163.webp"
    },
    {
      "id":164,
      "name_category": "BTS V Wallpaper 4",
      "title":"BTS V Wallpaper",
      "image":"file:///android_asset/image/itxem164.webp"
    },
    {
      "id":165,
      "name_category": "BTS V Wallpaper 4",
      "title":"BTS V Wallpaper",
      "image":"file:///android_asset/image/itxem165.webp"
    },
    {
      "id":166,
      "name_category": "BTS V Wallpaper 4",
      "title":"BTS V Wallpaper",
      "image":"file:///android_asset/image/itxem166.webp"
    },
    {
      "id":167,
      "name_category": "BTS V Wallpaper 4",
      "title":"BTS V Wallpaper",
      "image":"file:///android_asset/image/itxem167.webp"
    },
    {
      "id":168,
      "name_category": "BTS V Wallpaper 4",
      "title":"BTS V Wallpaper",
      "image":"file:///android_asset/image/itxem168.webp"
    },
    {
      "id":169,
      "name_category": "BTS V Wallpaper 4",
      "title":"BTS V Wallpaper",
      "image":"file:///android_asset/image/itxem169.webp"
    },
    {
      "id":170,
      "name_category": "BTS V Wallpaper 4",
      "title":"BTS V Wallpaper",
      "image":"file:///android_asset/image/itxem170.webp"
    },
	{
      "id":171,
      "name_category": "BTS V Wallpaper 4",
      "title":"BTS V Wallpaper",
      "image":"file:///android_asset/image/itxem171.webp"
    },
    {
      "id":172,
      "name_category": "BTS V Wallpaper 4",
      "title": "BTS V Wallpaper",
      "image": "file:///android_asset/image/itxem172.webp"
    },
    {
      "id":173,
      "name_category": "BTS V Wallpaper 4",
      "title":"BTS V Wallpaper",
      "image":"file:///android_asset/image/itxem173.webp"
    },
    {
      "id":174,
      "name_category": "BTS V Wallpaper 4",
      "title":"BTS V Wallpaper",
      "image":"file:///android_asset/image/itxem174.webp"
    },
    {
      "id":175,
      "name_category": "BTS V Wallpaper 4",
      "title":"BTS V Wallpaper",
      "image":"file:///android_asset/image/itxem175.webp"
    },
    {
      "id":176,
      "name_category": "BTS V Wallpaper 4",
      "title":"BTS V Wallpaper",
      "image":"file:///android_asset/image/itxem176.webp"
    },
    {
      "id":177,
      "name_category": "BTS V Wallpaper 4",
      "title":"BTS V Wallpaper",
      "image":"file:///android_asset/image/itxem177.webp"
    },
    {
      "id":178,
      "name_category": "BTS V Wallpaper 4",
      "title":"BTS V Wallpaper",
      "image":"file:///android_asset/image/itxem178.webp"
    },
    {
      "id":179,
      "name_category": "BTS V Wallpaper 4",
      "title":"BTS V Wallpaper",
      "image":"file:///android_asset/image/itxem179.webp"
    },
    {
      "id":180,
      "name_category": "BTS V Wallpaper 4",
      "title":"BTS V Wallpaper",
      "image":"file:///android_asset/image/itxem180.webp"
    },
	{
      "id":181,
      "name_category": "BTS V Wallpaper 4",
      "title":"BTS V Wallpaper",
      "image":"file:///android_asset/image/itxem181.webp"
    },
    {
      "id": 182,
      "name_category": "BTS V Wallpaper 4",
      "title": "BTS V Wallpaper",
      "image": "file:///android_asset/image/itxem182.webp"
    },
    {
      "id":183,
      "name_category": "BTS V Wallpaper 4",
      "title":"BTS V Wallpaper",
      "image":"file:///android_asset/image/itxem183.webp"
    },
    {
      "id":184,
      "name_category": "BTS V Wallpaper 4",
      "title":"BTS V Wallpaper",
      "image":"file:///android_asset/image/itxem184.webp"
    },
    {
      "id":185,
      "name_category": "BTS V Wallpaper 4",
      "title":"BTS V Wallpaper",
      "image":"file:///android_asset/image/itxem185.webp"
    },
    {
      "id":186,
      "name_category": "BTS V Wallpaper 4",
      "title":"BTS V Wallpaper",
      "image":"file:///android_asset/image/itxem186.webp"
    },
    {
      "id":187,
      "name_category": "BTS V Wallpaper 4",
      "title":"BTS V Wallpaper",
      "image":"file:///android_asset/image/itxem187.webp"
    },
    {
      "id":188,
      "name_category": "BTS V Wallpaper 4",
      "title":"BTS V Wallpaper",
      "image":"file:///android_asset/image/itxem188.webp"
    },
    {
      "id":189,
      "name_category": "BTS V Wallpaper 4",
      "title":"BTS V Wallpaper",
      "image":"file:///android_asset/image/itxem189.webp"
    },
    {
      "id":190,
      "name_category": "BTS V Wallpaper 4",
      "title":"BTS V Wallpaper",
      "image":"file:///android_asset/image/itxem190.webp"
    },
	{
      "id":191,
      "name_category": "BTS V Wallpaper 4",
      "title":"BTS V Wallpaper",
      "image":"file:///android_asset/image/itxem191.webp"
    },
    {
      "id": 192,
      "name_category": "BTS V Wallpaper 4",
      "title": "BTS V Wallpaper",
      "image": "file:///android_asset/image/itxem192.webp"
    },
    {
      "id":193,
      "name_category": "BTS V Wallpaper 4",
      "title":"BTS V Wallpaper",
      "image":"file:///android_asset/image/itxem193.webp"
    },
    {
      "id":194,
      "name_category": "BTS V Wallpaper 4",
      "title":"BTS V Wallpaper",
      "image":"file:///android_asset/image/itxem194.webp"
    },
    {
      "id":195,
      "name_category": "BTS V Wallpaper 4",
      "title":"BTS V Wallpaper",
      "image":"file:///android_asset/image/itxem195.webp"
    },
    {
      "id":196,
      "name_category": "BTS V Wallpaper 4",
      "title":"BTS V Wallpaper",
      "image":"file:///android_asset/image/itxem196.webp"
    },
    {
      "id":197,
      "name_category": "BTS V Wallpaper 4",
      "title":"BTS V Wallpaper",
      "image":"file:///android_asset/image/itxem197.webp"
    },
    {
      "id":198,
      "name_category": "BTS V Wallpaper 4",
      "title":"BTS V Wallpaper",
      "image":"file:///android_asset/image/itxem198.webp"
    },
    {
      "id":199,
      "name_category": "BTS V Wallpaper 4",
      "title":"BTS V Wallpaper",
      "image":"file:///android_asset/image/itxem199.webp"
    },
    {
      "id":200,
      "name_category": "BTS V Wallpaper 4",
      "title":"BTS V Wallpaper",
      "image":"file:///android_asset/image/itxem200.webp"
    },
	{
      "id":201,
      "name_category": "BTS V Wallpaper 5",
      "title":"BTS V Wallpaper",
      "image":"file:///android_asset/image/itxem201.webp"
    },
    {
      "id": 202,
      "name_category": "BTS V Wallpaper 5",
      "title": "BTS V Wallpaper",
      "image": "file:///android_asset/image/itxem202.webp"
    },
    {
      "id":203,
      "name_category": "BTS V Wallpaper 5",
      "title":"BTS V Wallpaper",
      "image":"file:///android_asset/image/itxem203.webp"
    },
    {
      "id":204,
      "name_category": "BTS V Wallpaper 5",
      "title":"BTS V Wallpaper",
      "image":"file:///android_asset/image/itxem204.webp"
    },
    {
      "id":205,
      "name_category": "BTS V Wallpaper 5",
      "title":"BTS V Wallpaper",
      "image":"file:///android_asset/image/itxem205.webp"
    },
    {
      "id":206,
      "name_category": "BTS V Wallpaper 5",
      "title":"BTS V Wallpaper",
      "image":"file:///android_asset/image/itxem206.webp"
    },
    {
      "id":207,
      "name_category": "BTS V Wallpaper 5",
      "title":"BTS V Wallpaper",
      "image":"file:///android_asset/image/itxem207.webp"
    },
    {
      "id":208,
      "name_category": "BTS V Wallpaper 5",
      "title":"BTS V Wallpaper",
      "image":"file:///android_asset/image/itxem208.webp"
    },
    {
      "id":209,
      "name_category": "BTS V Wallpaper 5",
      "title":"BTS V Wallpaper",
      "image":"file:///android_asset/image/itxem209.webp"
    },
    {
      "id":210,
      "name_category": "BTS V Wallpaper 5",
      "title":"BTS V Wallpaper",
      "image":"file:///android_asset/image/itxem210.webp"
    },
	{
      "id":211,
      "name_category": "BTS V Wallpaper 5",
      "title":"BTS V Wallpaper",
      "image":"file:///android_asset/image/itxem211.webp"
    },
    {
      "id": 212,
      "name_category": "BTS V Wallpaper 5",
      "title": "BTS V Wallpaper",
      "image": "file:///android_asset/image/itxem212.webp"
    },
    {
      "id":213,
      "name_category": "BTS V Wallpaper 5",
      "title":"BTS V Wallpaper",
      "image":"file:///android_asset/image/itxem213.webp"
    },
    {
      "id":214,
      "name_category": "BTS V Wallpaper 5",
      "title":"BTS V Wallpaper",
      "image":"file:///android_asset/image/itxem214.webp"
    },
    {
      "id":215,
      "name_category": "BTS V Wallpaper 5",
      "title":"BTS V Wallpaper",
      "image":"file:///android_asset/image/itxem215.webp"
    },
    {
      "id":216,
      "name_category": "BTS V Wallpaper 5",
      "title":"BTS V Wallpaper",
      "image":"file:///android_asset/image/itxem216.webp"
    },
    {
      "id":217,
      "name_category": "BTS V Wallpaper 5",
      "title":"BTS V Wallpaper",
      "image":"file:///android_asset/image/itxem217.webp"
    },
    {
      "id":218,
      "name_category": "BTS V Wallpaper 5",
      "title":"BTS V Wallpaper",
      "image":"file:///android_asset/image/itxem218.webp"
    },
    {
      "id":219,
      "name_category": "BTS V Wallpaper 5",
      "title":"BTS V Wallpaper",
      "image":"file:///android_asset/image/itxem219.webp"
    },
    {
      "id":220,
      "name_category": "BTS V Wallpaper 5",
      "title":"BTS V Wallpaper",
      "image":"file:///android_asset/image/itxem220.webp"
    },
	{
      "id":221,
      "name_category": "BTS V Wallpaper 5",
      "title":"BTS V Wallpaper",
      "image":"file:///android_asset/image/itxem221.webp"
    },
    {
      "id": 222,
      "name_category": "BTS V Wallpaper 5",
      "title": "BTS V Wallpaper",
      "image": "file:///android_asset/image/itxem222.webp"
    },
    {
      "id":223,
      "name_category": "BTS V Wallpaper 5",
      "title":"BTS V Wallpaper",
      "image":"file:///android_asset/image/itxem223.webp"
    },
    {
      "id":224,
      "name_category": "BTS V Wallpaper 5",
      "title":"BTS V Wallpaper",
      "image":"file:///android_asset/image/itxem224.webp"
    },
    {
      "id":225,
      "name_category": "BTS V Wallpaper 5",
      "title":"BTS V Wallpaper",
      "image":"file:///android_asset/image/itxem225.webp"
    },
    {
      "id":226,
      "name_category": "BTS V Wallpaper 5",
      "title":"BTS V Wallpaper",
      "image":"file:///android_asset/image/itxem226.webp"
    },
    {
      "id":227,
      "name_category": "BTS V Wallpaper 5",
      "title":"BTS V Wallpaper",
      "image":"file:///android_asset/image/itxem227.webp"
    },
    {
      "id":228,
      "name_category": "BTS V Wallpaper 5",
      "title":"BTS V Wallpaper",
      "image":"file:///android_asset/image/itxem228.webp"
    },
    {
      "id":229,
      "name_category": "BTS V Wallpaper 5",
      "title":"BTS V Wallpaper",
      "image":"file:///android_asset/image/itxem229.webp"
    },
    {
      "id":230,
      "name_category": "BTS V Wallpaper 5",
      "title":"BTS V Wallpaper",
      "image":"file:///android_asset/image/itxem230.webp"
    },
	{
      "id":231,
      "name_category": "BTS V Wallpaper 5",
      "title":"BTS V Wallpaper",
      "image":"file:///android_asset/image/itxem231.webp"
    },
    {
      "id": 232,
      "name_category": "BTS V Wallpaper 5",
      "title": "BTS V Wallpaper",
      "image": "file:///android_asset/image/itxem232.webp"
    },
    {
      "id":233,
      "name_category": "BTS V Wallpaper 5",
      "title":"BTS V Wallpaper",
      "image":"file:///android_asset/image/itxem233.webp"
    },
    {
      "id":234,
      "name_category": "BTS V Wallpaper 5",
      "title":"BTS V Wallpaper",
      "image":"file:///android_asset/image/itxem234.webp"
    },
    {
      "id":235,
      "name_category": "BTS V Wallpaper 5",
      "title":"BTS V Wallpaper",
      "image":"file:///android_asset/image/itxem235.webp"
    },
    {
      "id":236,
      "name_category": "BTS V Wallpaper 5",
      "title":"BTS V Wallpaper",
      "image":"file:///android_asset/image/itxem236.webp"
    },
    {
      "id":237,
      "name_category": "BTS V Wallpaper 5",
      "title":"BTS V Wallpaper",
      "image":"file:///android_asset/image/itxem237.webp"
    },
    {
      "id":238,
      "name_category": "BTS V Wallpaper 5",
      "title":"BTS V Wallpaper",
      "image":"file:///android_asset/image/itxem238.webp"
    },
    {
      "id":239,
      "name_category": "BTS V Wallpaper 5",
      "title":"BTS V Wallpaper",
      "image":"file:///android_asset/image/itxem239.webp"
    },
    {
      "id":240,
      "name_category": "BTS V Wallpaper 5",
      "title":"BTS V Wallpaper",
      "image":"file:///android_asset/image/itxem240.webp"
    },
	{
      "id":241,
      "name_category": "BTS V Wallpaper 5",
      "title":"BTS V Wallpaper",
      "image":"file:///android_asset/image/itxem241.webp"
    },
    {
      "id": 242,
      "name_category": "BTS V Wallpaper 5",
      "title": "BTS V Wallpaper",
      "image": "file:///android_asset/image/itxem242.webp"
    },
    {
      "id":243,
      "name_category": "BTS V Wallpaper 5",
      "title":"BTS V Wallpaper",
      "image":"file:///android_asset/image/itxem243.webp"
    },
    {
      "id":244,
      "name_category": "BTS V Wallpaper 5",
      "title":"BTS V Wallpaper",
      "image":"file:///android_asset/image/itxem244.webp"
    },
    {
      "id":245,
      "name_category": "BTS V Wallpaper 5",
      "title":"BTS V Wallpaper",
      "image":"file:///android_asset/image/itxem245.webp"
    },
    {
      "id":246,
      "name_category": "BTS V Wallpaper 5",
      "title":"BTS V Wallpaper",
      "image":"file:///android_asset/image/itxem246.webp"
    },
    {
      "id":247,
      "name_category": "BTS V Wallpaper 5",
      "title":"BTS V Wallpaper",
      "image":"file:///android_asset/image/itxem247.webp"
    },
    {
      "id":248,
      "name_category": "BTS V Wallpaper 5",
      "title":"BTS V Wallpaper",
      "image":"file:///android_asset/image/itxem248.webp"
    },
    {
      "id":249,
      "name_category": "BTS V Wallpaper 5",
      "title":"BTS V Wallpaper",
      "image":"file:///android_asset/image/itxem249.webp"
    },
    {
      "id":250,
      "name_category": "BTS V Wallpaper 5",
      "title":"BTS V Wallpaper",
      "image":"file:///android_asset/image/itxem250.webp"
    },
	{
      "id":251,
      "name_category": "BTS V Wallpaper 6",
      "title":"BTS V Wallpaper",
      "image":"file:///android_asset/image/itxem251.webp"
    },
    {
      "id": 252,
      "name_category": "BTS V Wallpaper 6",
      "title": "BTS V Wallpaper",
      "image": "file:///android_asset/image/itxem252.webp"
    },
    {
      "id":253,
      "name_category": "BTS V Wallpaper 6",
      "title":"BTS V Wallpaper",
      "image":"file:///android_asset/image/itxem253.webp"
    },
    {
      "id":254,
      "name_category": "BTS V Wallpaper 6",
      "title":"BTS V Wallpaper",
      "image":"file:///android_asset/image/itxem254.webp"
    },
    {
      "id":255,
      "name_category": "BTS V Wallpaper 6",
      "title":"BTS V Wallpaper",
      "image":"file:///android_asset/image/itxem255.webp"
    },
    {
      "id":256,
      "name_category": "BTS V Wallpaper 6",
      "title":"BTS V Wallpaper",
      "image":"file:///android_asset/image/itxem256.webp"
    },
    {
      "id":257,
      "name_category": "BTS V Wallpaper 6",
      "title":"BTS V Wallpaper",
      "image":"file:///android_asset/image/itxem257.webp"
    },
    {
      "id":258,
      "name_category": "BTS V Wallpaper 6",
      "title":"BTS V Wallpaper",
      "image":"file:///android_asset/image/itxem258.webp"
    },
    {
      "id":259,
      "name_category": "BTS V Wallpaper 6",
      "title":"BTS V Wallpaper",
      "image":"file:///android_asset/image/itxem259.webp"
    },
    {
      "id":260,
      "name_category": "BTS V Wallpaper 6",
      "title":"BTS V Wallpaper",
      "image":"file:///android_asset/image/itxem260.webp"
    },
	{
      "id":261,
      "name_category": "BTS V Wallpaper 6",
      "title":"BTS V Wallpaper",
      "image":"file:///android_asset/image/itxem261.webp"
    },
    {
      "id": 262,
      "name_category": "BTS V Wallpaper 6",
      "title": "BTS V Wallpaper",
      "image": "file:///android_asset/image/itxem262.webp"
    },
    {
      "id":263,
      "name_category": "BTS V Wallpaper 6",
      "title":"BTS V Wallpaper",
      "image":"file:///android_asset/image/itxem263.webp"
    },
    {
      "id":264,
      "name_category": "BTS V Wallpaper 6",
      "title":"BTS V Wallpaper",
      "image":"file:///android_asset/image/itxem264.webp"
    },
    {
      "id":265,
      "name_category": "BTS V Wallpaper 6",
      "title":"BTS V Wallpaper",
      "image":"file:///android_asset/image/itxem265.webp"
    },
    {
      "id":266,
      "name_category": "BTS V Wallpaper 6",
      "title":"BTS V Wallpaper",
      "image":"file:///android_asset/image/itxem266.webp"
    },
    {
      "id":267,
      "name_category": "BTS V Wallpaper 6",
      "title":"BTS V Wallpaper",
      "image":"file:///android_asset/image/itxem267.webp"
    },
    {
      "id":268,
      "name_category": "BTS V Wallpaper 6",
      "title":"BTS V Wallpaper",
      "image":"file:///android_asset/image/itxem268.webp"
    },
    {
      "id":269,
      "name_category": "BTS V Wallpaper 6",
      "title":"BTS V Wallpaper",
      "image":"file:///android_asset/image/itxem269.webp"
    },
    {
      "id":270,
      "name_category": "BTS V Wallpaper 6",
      "title":"BTS V Wallpaper",
      "image":"file:///android_asset/image/itxem270.webp"
    },
	{
      "id":271,
      "name_category": "BTS V Wallpaper 6",
      "title":"BTS V Wallpaper",
      "image":"file:///android_asset/image/itxem271.webp"
    },
    {
      "id": 272,
      "name_category": "BTS V Wallpaper 6",
      "title": "BTS V Wallpaper",
      "image": "file:///android_asset/image/itxem272.webp"
    },
    {
      "id":273,
      "name_category": "BTS V Wallpaper 6",
      "title":"BTS V Wallpaper",
      "image":"file:///android_asset/image/itxem273.webp"
    },
    {
      "id":274,
      "name_category": "BTS V Wallpaper 6",
      "title":"BTS V Wallpaper",
      "image":"file:///android_asset/image/itxem274.webp"
    },
    {
      "id":275,
      "name_category": "BTS V Wallpaper 6",
      "title":"BTS V Wallpaper",
      "image":"file:///android_asset/image/itxem275.webp"
    },
    {
      "id":276,
      "name_category": "BTS V Wallpaper 6",
      "title":"BTS V Wallpaper",
      "image":"file:///android_asset/image/itxem276.webp"
    },
    {
      "id":277,
      "name_category": "BTS V Wallpaper 6",
      "title":"BTS V Wallpaper",
      "image":"file:///android_asset/image/itxem277.webp"
    },
    {
      "id":278,
      "name_category": "BTS V Wallpaper 6",
      "title":"BTS V Wallpaper",
      "image":"file:///android_asset/image/itxem278.webp"
    },
    {
      "id":279,
      "name_category": "BTS V Wallpaper 6",
      "title":"BTS V Wallpaper",
      "image":"file:///android_asset/image/itxem279.webp"
    },
    {
      "id":280,
      "name_category": "BTS V Wallpaper 6",
      "title":"BTS V Wallpaper",
      "image":"file:///android_asset/image/itxem280.webp"
    },
	{
      "id":281,
      "name_category": "BTS V Wallpaper 6",
      "title":"BTS V Wallpaper",
      "image":"file:///android_asset/image/itxem281.webp"
    },
    {
      "id": 282,
      "name_category": "BTS V Wallpaper 6",
      "title": "BTS V Wallpaper",
      "image": "file:///android_asset/image/itxem282.webp"
    },
    {
      "id":283,
      "name_category": "BTS V Wallpaper 6",
      "title":"BTS V Wallpaper",
      "image":"file:///android_asset/image/itxem283.webp"
    },
    {
      "id":284,
      "name_category": "BTS V Wallpaper 6",
      "title":"BTS V Wallpaper",
      "image":"file:///android_asset/image/itxem284.webp"
    },
    {
      "id":285,
      "name_category": "BTS V Wallpaper 6",
      "title":"BTS V Wallpaper",
      "image":"file:///android_asset/image/itxem285.webp"
    },
    {
      "id":286,
      "name_category": "BTS V Wallpaper 6",
      "title":"BTS V Wallpaper",
      "image":"file:///android_asset/image/itxem286.webp"
    },
    {
      "id":287,
      "name_category": "BTS V Wallpaper 6",
      "title":"BTS V Wallpaper",
      "image":"file:///android_asset/image/itxem287.webp"
    },
    {
      "id":288,
      "name_category": "BTS V Wallpaper 6",
      "title":"BTS V Wallpaper",
      "image":"file:///android_asset/image/itxem288.webp"
    },
    {
      "id":289,
      "name_category": "BTS V Wallpaper 6",
      "title":"BTS V Wallpaper",
      "image":"file:///android_asset/image/itxem289.webp"
    },
    {
      "id":290,
      "name_category": "BTS V Wallpaper 6",
      "title":"BTS V Wallpaper",
      "image":"file:///android_asset/image/itxem290.webp"
    },
	{
      "id":291,
      "name_category": "BTS V Wallpaper 6",
      "title":"BTS V Wallpaper",
      "image":"file:///android_asset/image/itxem291.webp"
    },
    {
      "id": 292,
      "name_category": "BTS V Wallpaper 6",
      "title": "BTS V Wallpaper",
      "image": "file:///android_asset/image/itxem292.webp"
    },
    {
      "id":293,
      "name_category": "BTS V Wallpaper 6",
      "title":"BTS V Wallpaper",
      "image":"file:///android_asset/image/itxem293.webp"
    },
    {
      "id":294,
      "name_category": "BTS V Wallpaper 6",
      "title":"BTS V Wallpaper",
      "image":"file:///android_asset/image/itxem294.webp"
    },
    {
      "id":295,
      "name_category": "BTS V Wallpaper 6",
      "title":"BTS V Wallpaper",
      "image":"file:///android_asset/image/itxem295.webp"
    },
    {
      "id":296,
      "name_category": "BTS V Wallpaper 6",
      "title":"BTS V Wallpaper",
      "image":"file:///android_asset/image/itxem296.webp"
    },
    {
      "id":297,
      "name_category": "BTS V Wallpaper 6",
      "title":"BTS V Wallpaper",
      "image":"file:///android_asset/image/itxem297.webp"
    },
    {
      "id":298,
      "name_category": "BTS V Wallpaper 6",
      "title":"BTS V Wallpaper",
      "image":"file:///android_asset/image/itxem298.webp"
    },
    {
      "id":299,
      "name_category": "BTS V Wallpaper 6",
      "title":"BTS V Wallpaper",
      "image":"file:///android_asset/image/itxem299.webp"
    },
    {
      "id":300,
      "name_category": "BTS V Wallpaper 6",
      "title":"BTS V Wallpaper",
      "image":"file:///android_asset/image/itxem300.webp"
    }
  ]
}